setuptools_git_version_cc.py
setuptools_git_version_cc-3.0.4.dist-info/METADATA
setuptools_git_version_cc-3.0.4.dist-info/WHEEL
setuptools_git_version_cc-3.0.4.dist-info/entry_points.txt
setuptools_git_version_cc-3.0.4.dist-info/top_level.txt
setuptools_git_version_cc-3.0.4.dist-info/RECORD
